pymojeek/__init__.py
pymojeek-0.1.2.dist-info/LICENSE
pymojeek-0.1.2.dist-info/METADATA
pymojeek-0.1.2.dist-info/WHEEL
pymojeek-0.1.2.dist-info/top_level.txt
pymojeek-0.1.2.dist-info/RECORD
